[
  {
    "a": {
      "x": 0,
      "y": 0
    },
    "b": {
      "x": -69,
      "y": 148
    },
    "c": {
      "x": 18,
      "y": 111
    },
    "x": -52.715053763440864,
    "y": 65.50784655623366,
    "r": 7070.154853717515,
    "boundingBox": {
      "x": -69,
      "y": 0,
      "width": 87,
      "height": 148
    },
    "fill": "rgba(255, 255, 255, 1)",
    "strokeColor": "rgba(255, 255, 255, 1)",
    "strokeWidth": 0,
    "lineJoin": "miter"
  },
  {
    "a": {
      "x": -69,
      "y": 148
    },
    "b": {
      "x": 18,
      "y": 178
    },
    "c": {
      "x": 18,
      "y": 111
    },
    "x": -19.120689655172413,
    "y": 144.5,
    "r": 2500.1956004756244,
    "boundingBox": {
      "x": -69,
      "y": 111,
      "width": 87,
      "height": 67
    },
    "fill": "rgba(255, 255, 255, 1)",
    "strokeColor": "rgba(255, 255, 255, 1)",
    "strokeWidth": 0,
    "lineJoin": "miter"
  },
  {
    "a": {
      "x": -69,
      "y": 148
    },
    "b": {
      "x": 0,
      "y": 222
    },
    "c": {
      "x": 18,
      "y": 178
    },
    "x": -32.41620879120879,
    "y": 183.0570054945055,
    "r": 2567.367413450217,
    "boundingBox": {
      "x": -69,
      "y": 148,
      "width": 87,
      "height": 74
    },
    "fill": "rgba(255, 254, 255, 1)",
    "strokeColor": "rgba(255, 254, 255, 1)",
    "strokeWidth": 0,
    "lineJoin": "miter"
  },
  {
    "a": {
      "x": 0,
      "y": 0
    },
    "b": {
      "x": 18,
      "y": 111
    },
    "c": {
      "x": 41,
      "y": 52
    },
    "x": -23.62448132780083,
    "y": 60.79045643153527,
    "r": 4253.595711161997,
    "boundingBox": {
      "x": 0,
      "y": 0,
      "width": 41,
      "height": 111
    },
    "fill": "rgba(255, 255, 255, 1)",
    "strokeColor": "rgba(255, 255, 255, 1)",
    "strokeWidth": 0,
    "lineJoin": "miter"
  },
  {
    "a": {
      "x": 41,
      "y": 52
    },
    "b": {
      "x": 18,
      "y": 111
    },
    "c": {
      "x": 48,
      "y": 84
    },
    "x": 12.7088772845953,
    "y": 74.95430809399478,
    "r": 1327.287884572122,
    "boundingBox": {
      "x": 18,
      "y": 52,
      "width": 30,
      "height": 59
    },
    "fill": "rgba(255, 255, 255, 1)",
    "strokeColor": "rgba(255, 255, 255, 1)",
    "strokeWidth": 0,
    "lineJoin": "miter"
  },
  {
    "a": {
      "x": 18,
      "y": 111
    },
    "b": {
      "x": 46,
      "y": 94
    },
    "c": {
      "x": 48,
      "y": 84
    },
    "x": 20.597560975609756,
    "y": 83.71951219512195,
    "r": 750.9723378941108,
    "boundingBox": {
      "x": 18,
      "y": 84,
      "width": 30,
      "height": 27
    },
    "fill": "rgba(255, 255, 255, 1)",
    "strokeColor": "rgba(255, 255, 255, 1)",
    "strokeWidth": 0,
    "lineJoin": "miter"
  },
  {
    "a": {
      "x": 41,
      "y": 52
    },
    "b": {
      "x": 48,
      "y": 84
    },
    "c": {
      "x": 54,
      "y": 66
    },
    "x": 35.74528301886792,
    "y": 69.91509433962264,
    "r": 348.56265574937703,
    "boundingBox": {
      "x": 41,
      "y": 52,
      "width": 13,
      "height": 32
    },
    "fill": "rgba(32, 32, 32, 1)",
    "strokeColor": "rgba(32, 32, 32, 1)",
    "strokeWidth": 0,
    "lineJoin": "miter"
  },
  {
    "a": {
      "x": 0,
      "y": 0
    },
    "b": {
      "x": 41,
      "y": 52
    },
    "c": {
      "x": 54,
      "y": 24
    },
    "x": 20.92763157894737,
    "y": 25.66282894736842,
    "r": 1096.5465530860458,
    "boundingBox": {
      "x": 0,
      "y": 0,
      "width": 54,
      "height": 52
    },
    "fill": "rgba(248, 246, 249, 1)",
    "strokeColor": "rgba(248, 246, 249, 1)",
    "strokeWidth": 0,
    "lineJoin": "miter"
  },
  {
    "a": {
      "x": 18,
      "y": 111
    },
    "b": {
      "x": 18,
      "y": 178
    },
    "c": {
      "x": 52,
      "y": 162
    },
    "x": 23,
    "y": 144.5,
    "r": 1147.25,
    "boundingBox": {
      "x": 18,
      "y": 111,
      "width": 34,
      "height": 67
    },
    "fill": "rgba(255, 255, 255, 1)",
    "strokeColor": "rgba(255, 255, 255, 1)",
    "strokeWidth": 0,
    "lineJoin": "miter"
  },
  {
    "a": {
      "x": 18,
      "y": 111
    },
    "b": {
      "x": 52,
      "y": 162
    },
    "c": {
      "x": 64,
      "y": 136
    },
    "x": 33.32954545454545,
    "y": 137.61363636363637,
    "r": 943.2806043388434,
    "boundingBox": {
      "x": 18,
      "y": 111,
      "width": 46,
      "height": 51
    },
    "fill": "rgba(255, 255, 255, 1)",
    "strokeColor": "rgba(255, 255, 255, 1)",
    "strokeWidth": 0,
    "lineJoin": "miter"
  },
  {
    "a": {
      "x": 64,
      "y": 136
    },
    "b": {
      "x": 52,
      "y": 162
    },
    "c": {
      "x": 66,
      "y": 142
    },
    "x": 48.354838709677416,
    "y": 144.5483870967742,
    "r": 317.84599375650396,
    "boundingBox": {
      "x": 52,
      "y": 136,
      "width": 14,
      "height": 26
    },
    "fill": "rgba(255, 255, 255, 1)",
    "strokeColor": "rgba(255, 255, 255, 1)",
    "strokeWidth": 0,
    "lineJoin": "miter"
  },
  {
    "a": {
      "x": 46,
      "y": 94
    },
    "b": {
      "x": 18,
      "y": 111
    },
    "c": {
      "x": 64,
      "y": 136
    },
    "x": 42.77125506072875,
    "y": 120.24089068825911,
    "r": 699.0091379960336,
    "boundingBox": {
      "x": 18,
      "y": 94,
      "width": 46,
      "height": 42
    },
    "fill": "rgba(255, 255, 255, 1)",
    "strokeColor": "rgba(255, 255, 255, 1)",
    "strokeWidth": 0,
    "lineJoin": "miter"
  },
  {
    "a": {
      "x": 70,
      "y": 76
    },
    "b": {
      "x": 48,
      "y": 84
    },
    "c": {
      "x": 70,
      "y": 80
    },
    "x": 58.27272727272727,
    "y": 78,
    "r": 141.5289256198347,
    "boundingBox": {
      "x": 48,
      "y": 76,
      "width": 22,
      "height": 8
    },
    "fill": "rgba(69, 67, 70, 1)",
    "strokeColor": "rgba(69, 67, 70, 1)",
    "strokeWidth": 0,
    "lineJoin": "miter"
  },
  {
    "a": {
      "x": 54,
      "y": 66
    },
    "b": {
      "x": 48,
      "y": 84
    },
    "c": {
      "x": 70,
      "y": 76
    },
    "x": 58.03448275862069,
    "y": 77.34482758620689,
    "r": 144.98216409036849,
    "boundingBox": {
      "x": 48,
      "y": 66,
      "width": 22,
      "height": 18
    },
    "fill": "rgba(86, 84, 87, 1)",
    "strokeColor": "rgba(86, 84, 87, 1)",
    "strokeWidth": 0,
    "lineJoin": "miter"
  },
  {
    "a": {
      "x": 0,
      "y": 0
    },
    "b": {
      "x": 54,
      "y": 24
    },
    "c": {
      "x": 74,
      "y": 0
    },
    "x": 37,
    "y": -10.5,
    "r": 1479.25,
    "boundingBox": {
      "x": 0,
      "y": 0,
      "width": 74,
      "height": 24
    },
    "fill": "rgba(242, 240, 243, 1)",
    "strokeColor": "rgba(242, 240, 243, 1)",
    "strokeWidth": 0,
    "lineJoin": "miter"
  },
  {
    "a": {
      "x": 67,
      "y": -36
    },
    "b": {
      "x": 0,
      "y": 0
    },
    "c": {
      "x": 74,
      "y": 0
    },
    "x": 37,
    "y": -11.48611111111111,
    "r": 1500.9307484567903,
    "boundingBox": {
      "x": 0,
      "y": -36,
      "width": 74,
      "height": 36
    },
    "fill": "rgba(237, 235, 238, 1)",
    "strokeColor": "rgba(237, 235, 238, 1)",
    "strokeWidth": 0,
    "lineJoin": "miter"
  },
  {
    "a": {
      "x": 66,
      "y": 142
    },
    "b": {
      "x": 52,
      "y": 162
    },
    "c": {
      "x": 74,
      "y": 154
    },
    "x": 61.4390243902439,
    "y": 153.70731707317074,
    "r": 157.86377156454517,
    "boundingBox": {
      "x": 52,
      "y": 142,
      "width": 22,
      "height": 20
    },
    "fill": "rgba(18, 18, 18, 1)",
    "strokeColor": "rgba(18, 18, 18, 1)",
    "strokeWidth": 0,
    "lineJoin": "miter"
  },
  {
    "a": {
      "x": 48,
      "y": 84
    },
    "b": {
      "x": 46,
      "y": 94
    },
    "c": {
      "x": 70,
      "y": 80
    },
    "x": 60.77358490566038,
    "y": 91.75471698113208,
    "r": 223.30010679957286,
    "boundingBox": {
      "x": 46,
      "y": 80,
      "width": 24,
      "height": 14
    },
    "fill": "rgba(56, 54, 57, 1)",
    "strokeColor": "rgba(56, 54, 57, 1)",
    "strokeWidth": 0,
    "lineJoin": "miter"
  },
  {
    "a": {
      "x": 52,
      "y": 162
    },
    "b": {
      "x": 18,
      "y": 178
    },
    "c": {
      "x": 76,
      "y": 196
    },
    "x": 45.41038961038961,
    "y": 192.12207792207792,
    "r": 950.7625434305953,
    "boundingBox": {
      "x": 18,
      "y": 162,
      "width": 58,
      "height": 34
    },
    "fill": "rgba(31, 29, 34, 1)",
    "strokeColor": "rgba(31, 29, 34, 1)",
    "strokeWidth": 0,
    "lineJoin": "miter"
  },
  {
    "a": {
      "x": 74,
      "y": 0
    },
    "b": {
      "x": 54,
      "y": 24
    },
    "c": {
      "x": 78,
      "y": 8
    },
    "x": 62.5,
    "y": 10.75,
    "r": 247.8125,
    "boundingBox": {
      "x": 54,
      "y": 0,
      "width": 24,
      "height": 24
    },
    "fill": "rgba(249, 247, 250, 1)",
    "strokeColor": "rgba(249, 247, 250, 1)",
    "strokeWidth": 0,
    "lineJoin": "miter"
  },
  {
    "a": {
      "x": 18,
      "y": 178
    },
    "b": {
      "x": 0,
      "y": 222
    },
    "c": {
      "x": 76,
      "y": 196
    },
    "x": 39.139082058414466,
    "y": 212.32962447844227,
    "r": 1625.383907103243,
    "boundingBox": {
      "x": 0,
      "y": 178,
      "width": 76,
      "height": 44
    },
    "fill": "rgba(40, 38, 41, 1)",
    "strokeColor": "rgba(40, 38, 41, 1)",
    "strokeWidth": 0,
    "lineJoin": "miter"
  },
  {
    "a": {
      "x": 76,
      "y": 172
    },
    "b": {
      "x": 52,
      "y": 162
    },
    "c": {
      "x": 76,
      "y": 196
    },
    "x": 56.916666666666664,
    "y": 184,
    "r": 508.1736111111112,
    "boundingBox": {
      "x": 52,
      "y": 162,
      "width": 24,
      "height": 34
    },
    "fill": "rgba(35, 33, 36, 1)",
    "strokeColor": "rgba(35, 33, 36, 1)",
    "strokeWidth": 0,
    "lineJoin": "miter"
  },
  {
    "a": {
      "x": 74,
      "y": 154
    },
    "b": {
      "x": 52,
      "y": 162
    },
    "c": {
      "x": 76,
      "y": 172
    },
    "x": 65.2135922330097,
    "y": 164.0873786407767,
    "r": 178.95616929022546,
    "boundingBox": {
      "x": 52,
      "y": 154,
      "width": 24,
      "height": 18
    },
    "fill": "rgba(21, 19, 22, 1)",
    "strokeColor": "rgba(21, 19, 22, 1)",
    "strokeWidth": 0,
    "lineJoin": "miter"
  },
  {
    "a": {
      "x": 70,
      "y": 76
    },
    "b": {
      "x": 70,
      "y": 80
    },
    "c": {
      "x": 80,
      "y": 72
    },
    "x": 76.6,
    "y": 78,
    "r": 47.559999999999924,
    "boundingBox": {
      "x": 70,
      "y": 72,
      "width": 10,
      "height": 8
    },
    "fill": "rgba(111, 109, 112, 1)",
    "strokeColor": "rgba(111, 109, 112, 1)",
    "strokeWidth": 0,
    "lineJoin": "miter"
  },
  {
    "a": {
      "x": 54,
      "y": 66
    },
    "b": {
      "x": 70,
      "y": 76
    },
    "c": {
      "x": 80,
      "y": 72
    },
    "x": 69.1951219512195,
    "y": 59.48780487804878,
    "r": 273.30041641879814,
    "boundingBox": {
      "x": 54,
      "y": 66,
      "width": 26,
      "height": 10
    },
    "fill": "rgba(147, 145, 148, 1)",
    "strokeColor": "rgba(147, 145, 148, 1)",
    "strokeWidth": 0,
    "lineJoin": "miter"
  },
  {
    "a": {
      "x": 74,
      "y": 154
    },
    "b": {
      "x": 76,
      "y": 172
    },
    "c": {
      "x": 80,
      "y": 158
    },
    "x": 72.12,
    "y": 163.32,
    "r": 90.39679999999984,
    "boundingBox": {
      "x": 74,
      "y": 154,
      "width": 6,
      "height": 18
    },
    "fill": "rgba(108, 106, 109, 1)",
    "strokeColor": "rgba(108, 106, 109, 1)",
    "strokeWidth": 0,
    "lineJoin": "miter"
  },
  {
    "a": {
      "x": 78,
      "y": 8
    },
    "b": {
      "x": 54,
      "y": 24
    },
    "c": {
      "x": 78,
      "y": 34
    },
    "x": 69.33333333333333,
    "y": 21,
    "r": 244.1111111111112,
    "boundingBox": {
      "x": 54,
      "y": 8,
      "width": 24,
      "height": 26
    },
    "fill": "rgba(52, 50, 53, 1)",
    "strokeColor": "rgba(52, 50, 53, 1)",
    "strokeWidth": 0,
    "lineJoin": "miter"
  },
  {
    "a": {
      "x": 54,
      "y": 24
    },
    "b": {
      "x": 41,
      "y": 52
    },
    "c": {
      "x": 78,
      "y": 34
    },
    "x": 59.85910224438903,
    "y": 43.738154613466335,
    "r": 423.9238266553069,
    "boundingBox": {
      "x": 41,
      "y": 24,
      "width": 37,
      "height": 28
    },
    "fill": "rgba(33, 31, 34, 1)",
    "strokeColor": "rgba(33, 31, 34, 1)",
    "strokeWidth": 0,
    "lineJoin": "miter"
  },
  {
    "a": {
      "x": 41,
      "y": 52
    },
    "b": {
      "x": 54,
      "y": 66
    },
    "c": {
      "x": 78,
      "y": 34
    },
    "x": 61.12765957446808,
    "y": 46.34574468085106,
    "r": 437.09328315980076,
    "boundingBox": {
      "x": 41,
      "y": 34,
      "width": 37,
      "height": 32
    },
    "fill": "rgba(102, 100, 103, 1)",
    "strokeColor": "rgba(102, 100, 103, 1)",
    "strokeWidth": 0,
    "lineJoin": "miter"
  },
  {
    "a": {
      "x": 80,
      "y": 158
    },
    "b": {
      "x": 76,
      "y": 172
    },
    "c": {
      "x": 88,
      "y": 166
    },
    "x": 80.33333333333333,
    "y": 165.66666666666666,
    "r": 58.88888888888874,
    "boundingBox": {
      "x": 76,
      "y": 158,
      "width": 12,
      "height": 14
    },
    "fill": "rgba(132, 130, 133, 1)",
    "strokeColor": "rgba(132, 130, 133, 1)",
    "strokeWidth": 0,
    "lineJoin": "miter"
  },
  {
    "a": {
      "x": 78,
      "y": 34
    },
    "b": {
      "x": 54,
      "y": 66
    },
    "c": {
      "x": 80,
      "y": 72
    },
    "x": 70.59016393442623,
    "y": 53.442622950819676,
    "r": 432.92125772641776,
    "boundingBox": {
      "x": 54,
      "y": 34,
      "width": 26,
      "height": 38
    },
    "fill": "rgba(166, 164, 167, 1)",
    "strokeColor": "rgba(166, 164, 167, 1)",
    "strokeWidth": 0,
    "lineJoin": "miter"
  },
  {
    "a": {
      "x": 46,
      "y": 94
    },
    "b": {
      "x": 64,
      "y": 136
    },
    "c": {
      "x": 92,
      "y": 100
    },
    "x": 67.34210526315789,
    "y": 109.71052631578948,
    "r": 702.3060941828255,
    "boundingBox": {
      "x": 46,
      "y": 94,
      "width": 46,
      "height": 42
    },
    "fill": "rgba(133, 131, 134, 1)",
    "strokeColor": "rgba(133, 131, 134, 1)",
    "strokeWidth": 0,
    "lineJoin": "miter"
  },
  {
    "a": {
      "x": 70,
      "y": 80
    },
    "b": {
      "x": 46,
      "y": 94
    },
    "c": {
      "x": 92,
      "y": 100
    },
    "x": 68.05583756345177,
    "y": 104.23857868020305,
    "r": 591.2884640160788,
    "boundingBox": {
      "x": 46,
      "y": 80,
      "width": 46,
      "height": 20
    },
    "fill": "rgba(142, 140, 143, 1)",
    "strokeColor": "rgba(142, 140, 143, 1)",
    "strokeWidth": 0,
    "lineJoin": "miter"
  },
  {
    "a": {
      "x": 92,
      "y": 40
    },
    "b": {
      "x": 80,
      "y": 72
    },
    "c": {
      "x": 96,
      "y": 44
    },
    "x": 81.63636363636364,
    "y": 54.36363636363637,
    "r": 313.7190082644628,
    "boundingBox": {
      "x": 80,
      "y": 40,
      "width": 16,
      "height": 32
    },
    "fill": "rgba(209, 207, 210, 1)",
    "strokeColor": "rgba(209, 207, 210, 1)",
    "strokeWidth": 0,
    "lineJoin": "miter"
  },
  {
    "a": {
      "x": 80,
      "y": 72
    },
    "b": {
      "x": 70,
      "y": 80
    },
    "c": {
      "x": 92,
      "y": 100
    },
    "x": 83.76595744680851,
    "y": 86.95744680851064,
    "r": 237.9076505205976,
    "boundingBox": {
      "x": 70,
      "y": 72,
      "width": 22,
      "height": 28
    },
    "fill": "rgba(125, 123, 126, 1)",
    "strokeColor": "rgba(125, 123, 126, 1)",
    "strokeWidth": 0,
    "lineJoin": "miter"
  },
  {
    "a": {
      "x": 78,
      "y": 34
    },
    "b": {
      "x": 80,
      "y": 72
    },
    "c": {
      "x": 92,
      "y": 40
    },
    "x": 78.12307692307692,
    "y": 53.04615384615385,
    "r": 362.7711242603552,
    "boundingBox": {
      "x": 78,
      "y": 34,
      "width": 14,
      "height": 38
    },
    "fill": "rgba(158, 156, 159, 1)",
    "strokeColor": "rgba(158, 156, 159, 1)",
    "strokeWidth": 0,
    "lineJoin": "miter"
  },
  {
    "a": {
      "x": 78,
      "y": 8
    },
    "b": {
      "x": 78,
      "y": 34
    },
    "c": {
      "x": 102,
      "y": 14
    },
    "x": 87.5,
    "y": 21,
    "r": 259.25,
    "boundingBox": {
      "x": 78,
      "y": 8,
      "width": 24,
      "height": 26
    },
    "fill": "rgba(31, 29, 32, 1)",
    "strokeColor": "rgba(31, 29, 32, 1)",
    "strokeWidth": 0,
    "lineJoin": "miter"
  },
  {
    "a": {
      "x": 80,
      "y": 158
    },
    "b": {
      "x": 88,
      "y": 166
    },
    "c": {
      "x": 104,
      "y": 150
    },
    "x": 92,
    "y": 154,
    "r": 160,
    "boundingBox": {
      "x": 80,
      "y": 150,
      "width": 24,
      "height": 16
    },
    "fill": "rgba(53, 51, 54, 1)",
    "strokeColor": "rgba(53, 51, 54, 1)",
    "strokeWidth": 0,
    "lineJoin": "miter"
  },
  {
    "a": {
      "x": 92,
      "y": 100
    },
    "b": {
      "x": 64,
      "y": 136
    },
    "c": {
      "x": 106,
      "y": 112
    },
    "x": 84.42857142857143,
    "y": 123,
    "r": 586.3265306122448,
    "boundingBox": {
      "x": 64,
      "y": 100,
      "width": 42,
      "height": 36
    },
    "fill": "rgba(100, 100, 100, 1)",
    "strokeColor": "rgba(100, 100, 100, 1)",
    "strokeWidth": 0,
    "lineJoin": "miter"
  },
  {
    "a": {
      "x": 66,
      "y": 142
    },
    "b": {
      "x": 74,
      "y": 154
    },
    "c": {
      "x": 104,
      "y": 150
    },
    "x": 86.95918367346938,
    "y": 136.69387755102042,
    "r": 467.44231570179056,
    "boundingBox": {
      "x": 66,
      "y": 142,
      "width": 38,
      "height": 12
    },
    "fill": "rgba(55, 53, 56, 1)",
    "strokeColor": "rgba(55, 53, 56, 1)",
    "strokeWidth": 0,
    "lineJoin": "miter"
  },
  {
    "a": {
      "x": 74,
      "y": 154
    },
    "b": {
      "x": 80,
      "y": 158
    },
    "c": {
      "x": 104,
      "y": 150
    },
    "x": 87.44444444444444,
    "y": 140.33333333333334,
    "r": 367.53086419753055,
    "boundingBox": {
      "x": 74,
      "y": 150,
      "width": 30,
      "height": 8
    },
    "fill": "rgba(48, 46, 49, 1)",
    "strokeColor": "rgba(48, 46, 49, 1)",
    "strokeWidth": 0,
    "lineJoin": "miter"
  },
  {
    "a": {
      "x": 78,
      "y": 34
    },
    "b": {
      "x": 92,
      "y": 40
    },
    "c": {
      "x": 102,
      "y": 14
    },
    "x": 90.37735849056604,
    "y": 24.452830188679247,
    "r": 244.34745461018156,
    "boundingBox": {
      "x": 78,
      "y": 14,
      "width": 24,
      "height": 26
    },
    "fill": "rgba(54, 52, 55, 1)",
    "strokeColor": "rgba(54, 52, 55, 1)",
    "strokeWidth": 0,
    "lineJoin": "miter"
  },
  {
    "a": {
      "x": 76,
      "y": 172
    },
    "b": {
      "x": 76,
      "y": 196
    },
    "c": {
      "x": 88,
      "y": 166
    },
    "x": 89.5,
    "y": 184,
    "r": 326.25,
    "boundingBox": {
      "x": 76,
      "y": 166,
      "width": 12,
      "height": 30
    },
    "fill": "rgba(139, 137, 140, 1)",
    "strokeColor": "rgba(139, 137, 140, 1)",
    "strokeWidth": 0,
    "lineJoin": "miter"
  },
  {
    "a": {
      "x": 106,
      "y": 112
    },
    "b": {
      "x": 64,
      "y": 136
    },
    "c": {
      "x": 110,
      "y": 122
    },
    "x": 86.02325581395348,
    "y": 125.79069767441861,
    "r": 589.2536506219582,
    "boundingBox": {
      "x": 64,
      "y": 112,
      "width": 46,
      "height": 24
    },
    "fill": "rgba(158, 158, 158, 1)",
    "strokeColor": "rgba(158, 158, 158, 1)",
    "strokeWidth": 0,
    "lineJoin": "miter"
  },
  {
    "a": {
      "x": 64,
      "y": 136
    },
    "b": {
      "x": 66,
      "y": 142
    },
    "c": {
      "x": 110,
      "y": 122
    },
    "x": 87.73684210526316,
    "y": 131.42105263157896,
    "r": 584.4044321329642,
    "boundingBox": {
      "x": 64,
      "y": 122,
      "width": 46,
      "height": 20
    },
    "fill": "rgba(126, 124, 127, 1)",
    "strokeColor": "rgba(126, 124, 127, 1)",
    "strokeWidth": 0,
    "lineJoin": "miter"
  },
  {
    "a": {
      "x": 110,
      "y": 122
    },
    "b": {
      "x": 104,
      "y": 150
    },
    "c": {
      "x": 112,
      "y": 128
    },
    "x": 89.34782608695652,
    "y": 132.2173913043478,
    "r": 530.9073724007561,
    "boundingBox": {
      "x": 104,
      "y": 122,
      "width": 8,
      "height": 28
    },
    "fill": "rgba(158, 156, 159, 1)",
    "strokeColor": "rgba(158, 156, 159, 1)",
    "strokeWidth": 0,
    "lineJoin": "miter"
  },
  {
    "a": {
      "x": 66,
      "y": 142
    },
    "b": {
      "x": 104,
      "y": 150
    },
    "c": {
      "x": 110,
      "y": 122
    },
    "x": 87.96402877697842,
    "y": 131.9208633093525,
    "r": 584.0075565446928,
    "boundingBox": {
      "x": 66,
      "y": 122,
      "width": 44,
      "height": 28
    },
    "fill": "rgba(88, 86, 89, 1)",
    "strokeColor": "rgba(88, 86, 89, 1)",
    "strokeWidth": 0,
    "lineJoin": "miter"
  },
  {
    "a": {
      "x": 74,
      "y": 0
    },
    "b": {
      "x": 78,
      "y": 8
    },
    "c": {
      "x": 102,
      "y": 14
    },
    "x": 94,
    "y": -5,
    "r": 425,
    "boundingBox": {
      "x": 74,
      "y": 0,
      "width": 28,
      "height": 14
    },
    "fill": "rgba(253, 251, 254, 1)",
    "strokeColor": "rgba(253, 251, 254, 1)",
    "strokeWidth": 0,
    "lineJoin": "miter"
  },
  {
    "a": {
      "x": 88,
      "y": 166
    },
    "b": {
      "x": 76,
      "y": 196
    },
    "c": {
      "x": 116,
      "y": 182
    },
    "x": 95.02325581395348,
    "y": 186.2093023255814,
    "r": 457.7420227149814,
    "boundingBox": {
      "x": 76,
      "y": 166,
      "width": 40,
      "height": 30
    },
    "fill": "rgba(181, 179, 182, 1)",
    "strokeColor": "rgba(181, 179, 182, 1)",
    "strokeWidth": 0,
    "lineJoin": "miter"
  },
  {
    "a": {
      "x": 104,
      "y": 150
    },
    "b": {
      "x": 88,
      "y": 166
    },
    "c": {
      "x": 116,
      "y": 182
    },
    "x": 105.63636363636364,
    "y": 167.63636363636363,
    "r": 313.7190082644625,
    "boundingBox": {
      "x": 88,
      "y": 150,
      "width": 28,
      "height": 32
    },
    "fill": "rgba(128, 126, 129, 1)",
    "strokeColor": "rgba(128, 126, 129, 1)",
    "strokeWidth": 0,
    "lineJoin": "miter"
  },
  {
    "a": {
      "x": 92,
      "y": 40
    },
    "b": {
      "x": 96,
      "y": 44
    },
    "c": {
      "x": 102,
      "y": 14
    },
    "x": 105.66666666666667,
    "y": 30.333333333333332,
    "r": 280.2222222222224,
    "boundingBox": {
      "x": 92,
      "y": 14,
      "width": 10,
      "height": 30
    },
    "fill": "rgba(35, 35, 35, 1)",
    "strokeColor": "rgba(35, 35, 35, 1)",
    "strokeWidth": 0,
    "lineJoin": "miter"
  },
  {
    "a": {
      "x": 112,
      "y": 128
    },
    "b": {
      "x": 104,
      "y": 150
    },
    "c": {
      "x": 126,
      "y": 146
    },
    "x": 113.7433628318584,
    "y": 141.08849557522123,
    "r": 174.3480303860911,
    "boundingBox": {
      "x": 104,
      "y": 128,
      "width": 22,
      "height": 22
    },
    "fill": "rgba(165, 163, 166, 1)",
    "strokeColor": "rgba(165, 163, 166, 1)",
    "strokeWidth": 0,
    "lineJoin": "miter"
  },
  {
    "a": {
      "x": 76,
      "y": 196
    },
    "b": {
      "x": 0,
      "y": 222
    },
    "c": {
      "x": 129,
      "y": 275
    },
    "x": 57.41370902194527,
    "y": 265.7477648333785,
    "r": 5210.200911573187,
    "boundingBox": {
      "x": 0,
      "y": 196,
      "width": 129,
      "height": 79
    },
    "fill": "rgba(18, 16, 19, 1)",
    "strokeColor": "rgba(18, 16, 19, 1)",
    "strokeWidth": 0,
    "lineJoin": "miter"
  },
  {
    "a": {
      "x": 116,
      "y": 182
    },
    "b": {
      "x": 76,
      "y": 196
    },
    "c": {
      "x": 124,
      "y": 188
    },
    "x": 102.68181818181819,
    "y": 208.0909090909091,
    "r": 858.1095041322315,
    "boundingBox": {
      "x": 76,
      "y": 182,
      "width": 48,
      "height": 14
    },
    "fill": "rgba(30, 28, 31, 1)",
    "strokeColor": "rgba(30, 28, 31, 1)",
    "strokeWidth": 0,
    "lineJoin": "miter"
  },
  {
    "a": {
      "x": 124,
      "y": 188
    },
    "b": {
      "x": 76,
      "y": 196
    },
    "c": {
      "x": 132,
      "y": 208
    },
    "x": 102.6875,
    "y": 208.125,
    "r": 859.23828125,
    "boundingBox": {
      "x": 76,
      "y": 188,
      "width": 56,
      "height": 20
    },
    "fill": "rgba(44, 42, 45, 1)",
    "strokeColor": "rgba(44, 42, 45, 1)",
    "strokeWidth": 0,
    "lineJoin": "miter"
  },
  {
    "a": {
      "x": 96,
      "y": 44
    },
    "b": {
      "x": 80,
      "y": 72
    },
    "c": {
      "x": 132,
      "y": 56
    },
    "x": 107.6,
    "y": 69.2,
    "r": 769.6,
    "boundingBox": {
      "x": 80,
      "y": 44,
      "width": 52,
      "height": 28
    },
    "fill": "rgba(197, 195, 198, 1)",
    "strokeColor": "rgba(197, 195, 198, 1)",
    "strokeWidth": 0,
    "lineJoin": "miter"
  },
  {
    "a": {
      "x": 132,
      "y": 48
    },
    "b": {
      "x": 96,
      "y": 44
    },
    "c": {
      "x": 132,
      "y": 56
    },
    "x": 113.33333333333333,
    "y": 52,
    "r": 364.4444444444446,
    "boundingBox": {
      "x": 96,
      "y": 44,
      "width": 36,
      "height": 12
    },
    "fill": "rgba(189, 187, 190, 1)",
    "strokeColor": "rgba(189, 187, 190, 1)",
    "strokeWidth": 0,
    "lineJoin": "miter"
  },
  {
    "a": {
      "x": 104,
      "y": 150
    },
    "b": {
      "x": 116,
      "y": 182
    },
    "c": {
      "x": 126,
      "y": 146
    },
    "x": 117.74468085106383,
    "y": 163.09574468085106,
    "r": 360.41478044363953,
    "boundingBox": {
      "x": 104,
      "y": 146,
      "width": 22,
      "height": 36
    },
    "fill": "rgba(149, 147, 150, 1)",
    "strokeColor": "rgba(149, 147, 150, 1)",
    "strokeWidth": 0,
    "lineJoin": "miter"
  },
  {
    "a": {
      "x": 124,
      "y": 188
    },
    "b": {
      "x": 132,
      "y": 208
    },
    "c": {
      "x": 138,
      "y": 200
    },
    "x": 127.34782608695652,
    "y": 198.2608695652174,
    "r": 116.4933837429114,
    "boundingBox": {
      "x": 124,
      "y": 188,
      "width": 14,
      "height": 20
    },
    "fill": "rgba(224, 222, 225, 1)",
    "strokeColor": "rgba(224, 222, 225, 1)",
    "strokeWidth": 0,
    "lineJoin": "miter"
  },
  {
    "a": {
      "x": 106,
      "y": 112
    },
    "b": {
      "x": 110,
      "y": 122
    },
    "c": {
      "x": 138,
      "y": 106
    },
    "x": 122.4186046511628,
    "y": 111.23255813953489,
    "r": 270.1595457003787,
    "boundingBox": {
      "x": 106,
      "y": 106,
      "width": 32,
      "height": 16
    },
    "fill": "rgba(181, 179, 182, 1)",
    "strokeColor": "rgba(181, 179, 182, 1)",
    "strokeWidth": 0,
    "lineJoin": "miter"
  },
  {
    "a": {
      "x": 110,
      "y": 122
    },
    "b": {
      "x": 112,
      "y": 128
    },
    "c": {
      "x": 138,
      "y": 106
    },
    "x": 127.2,
    "y": 119.6,
    "r": 301.60000000000014,
    "boundingBox": {
      "x": 110,
      "y": 106,
      "width": 28,
      "height": 22
    },
    "fill": "rgba(175, 173, 176, 1)",
    "strokeColor": "rgba(175, 173, 176, 1)",
    "strokeWidth": 0,
    "lineJoin": "miter"
  },
  {
    "a": {
      "x": 76,
      "y": 196
    },
    "b": {
      "x": 129,
      "y": 275
    },
    "c": {
      "x": 136,
      "y": 216
    },
    "x": 94.34239130434783,
    "y": 240.97282608695653,
    "r": 2358.9984050094527,
    "boundingBox": {
      "x": 76,
      "y": 196,
      "width": 60,
      "height": 79
    },
    "fill": "rgba(28, 26, 29, 1)",
    "strokeColor": "rgba(28, 26, 29, 1)",
    "strokeWidth": 0,
    "lineJoin": "miter"
  },
  {
    "a": {
      "x": 132,
      "y": 208
    },
    "b": {
      "x": 76,
      "y": 196
    },
    "c": {
      "x": 136,
      "y": 216
    },
    "x": 98,
    "y": 230,
    "r": 1640,
    "boundingBox": {
      "x": 76,
      "y": 196,
      "width": 60,
      "height": 20
    },
    "fill": "rgba(44, 42, 45, 1)",
    "strokeColor": "rgba(44, 42, 45, 1)",
    "strokeWidth": 0,
    "lineJoin": "miter"
  },
  {
    "a": {
      "x": 80,
      "y": 72
    },
    "b": {
      "x": 92,
      "y": 100
    },
    "c": {
      "x": 132,
      "y": 56
    },
    "x": 109.6504854368932,
    "y": 75.86407766990291,
    "r": 894.0823828824583,
    "boundingBox": {
      "x": 80,
      "y": 56,
      "width": 52,
      "height": 44
    },
    "fill": "rgba(120, 118, 121, 1)",
    "strokeColor": "rgba(120, 118, 121, 1)",
    "strokeWidth": 0,
    "lineJoin": "miter"
  },
  {
    "a": {
      "x": 102,
      "y": 14
    },
    "b": {
      "x": 96,
      "y": 44
    },
    "c": {
      "x": 132,
      "y": 48
    },
    "x": 115.52173913043478,
    "y": 32.30434782608695,
    "r": 517.8865784499053,
    "boundingBox": {
      "x": 96,
      "y": 14,
      "width": 36,
      "height": 34
    },
    "fill": "rgba(108, 108, 108, 1)",
    "strokeColor": "rgba(108, 108, 108, 1)",
    "strokeWidth": 0,
    "lineJoin": "miter"
  },
  {
    "a": {
      "x": 67,
      "y": -36
    },
    "b": {
      "x": 74,
      "y": 0
    },
    "c": {
      "x": 102,
      "y": 14
    },
    "x": 103.73076923076923,
    "y": -24.46153846153846,
    "r": 1482.2855029585796,
    "boundingBox": {
      "x": 67,
      "y": -36,
      "width": 35,
      "height": 50
    },
    "fill": "rgba(247, 245, 248, 1)",
    "strokeColor": "rgba(247, 245, 248, 1)",
    "strokeWidth": 0,
    "lineJoin": "miter"
  },
  {
    "a": {
      "x": 92,
      "y": 100
    },
    "b": {
      "x": 106,
      "y": 112
    },
    "c": {
      "x": 146,
      "y": 86
    },
    "x": 116.94312796208531,
    "y": 85.06635071090048,
    "r": 845.1735136227848,
    "boundingBox": {
      "x": 92,
      "y": 86,
      "width": 54,
      "height": 26
    },
    "fill": "rgba(197, 195, 198, 1)",
    "strokeColor": "rgba(197, 195, 198, 1)",
    "strokeWidth": 0,
    "lineJoin": "miter"
  },
  {
    "a": {
      "x": 106,
      "y": 112
    },
    "b": {
      "x": 138,
      "y": 106
    },
    "c": {
      "x": 146,
      "y": 86
    },
    "x": 117.74324324324324,
    "y": 86.29729729729729,
    "r": 798.5326880934992,
    "boundingBox": {
      "x": 106,
      "y": 86,
      "width": 40,
      "height": 26
    },
    "fill": "rgba(187, 185, 188, 1)",
    "strokeColor": "rgba(187, 185, 188, 1)",
    "strokeWidth": 0,
    "lineJoin": "miter"
  },
  {
    "a": {
      "x": 132,
      "y": 56
    },
    "b": {
      "x": 92,
      "y": 100
    },
    "c": {
      "x": 146,
      "y": 86
    },
    "x": 116.0704845814978,
    "y": 81.70044052863436,
    "r": 914.262104834171,
    "boundingBox": {
      "x": 92,
      "y": 56,
      "width": 54,
      "height": 44
    },
    "fill": "rgba(160, 158, 161, 1)",
    "strokeColor": "rgba(160, 158, 161, 1)",
    "strokeWidth": 0,
    "lineJoin": "miter"
  },
  {
    "a": {
      "x": 132,
      "y": 208
    },
    "b": {
      "x": 136,
      "y": 216
    },
    "c": {
      "x": 138,
      "y": 200
    },
    "x": 141,
    "y": 208.5,
    "r": 81.25,
    "boundingBox": {
      "x": 132,
      "y": 200,
      "width": 6,
      "height": 16
    },
    "fill": "rgba(180, 178, 181, 1)",
    "strokeColor": "rgba(180, 178, 181, 1)",
    "strokeWidth": 0,
    "lineJoin": "miter"
  },
  {
    "a": {
      "x": 136,
      "y": 216
    },
    "b": {
      "x": 129,
      "y": 275
    },
    "c": {
      "x": 152,
      "y": 244
    },
    "x": 119.56140350877193,
    "y": 243.96491228070175,
    "r": 1052.2637734687596,
    "boundingBox": {
      "x": 129,
      "y": 216,
      "width": 23,
      "height": 59
    },
    "fill": "rgba(34, 32, 35, 1)",
    "strokeColor": "rgba(34, 32, 35, 1)",
    "strokeWidth": 0,
    "lineJoin": "miter"
  },
  {
    "a": {
      "x": 112,
      "y": 128
    },
    "b": {
      "x": 126,
      "y": 146
    },
    "c": {
      "x": 138,
      "y": 106
    },
    "x": 132.82474226804123,
    "y": 126.24742268041237,
    "r": 436.7414177914761,
    "boundingBox": {
      "x": 112,
      "y": 106,
      "width": 26,
      "height": 40
    },
    "fill": "rgba(174, 172, 175, 1)",
    "strokeColor": "rgba(174, 172, 175, 1)",
    "strokeWidth": 0,
    "lineJoin": "miter"
  },
  {
    "a": {
      "x": 116,
      "y": 182
    },
    "b": {
      "x": 124,
      "y": 188
    },
    "c": {
      "x": 126,
      "y": 146
    },
    "x": 133.20689655172413,
    "y": 167.39080459770116,
    "r": 509.50587924428515,
    "boundingBox": {
      "x": 116,
      "y": 146,
      "width": 10,
      "height": 42
    },
    "fill": "rgba(222, 220, 223, 1)",
    "strokeColor": "rgba(222, 220, 223, 1)",
    "strokeWidth": 0,
    "lineJoin": "miter"
  },
  {
    "a": {
      "x": 138,
      "y": 106
    },
    "b": {
      "x": 126,
      "y": 146
    },
    "c": {
      "x": 178,
      "y": 127
    },
    "x": 150.15334773218143,
    "y": 131.44600431965443,
    "r": 795.2029969351917,
    "boundingBox": {
      "x": 126,
      "y": 106,
      "width": 52,
      "height": 40
    },
    "fill": "rgba(255, 255, 255, 1)",
    "strokeColor": "rgba(255, 255, 255, 1)",
    "strokeWidth": 0,
    "lineJoin": "miter"
  },
  {
    "a": {
      "x": 146,
      "y": 86
    },
    "b": {
      "x": 138,
      "y": 106
    },
    "c": {
      "x": 178,
      "y": 127
    },
    "x": 164.11776859504133,
    "y": 104.84710743801652,
    "r": 683.4669976436035,
    "boundingBox": {
      "x": 138,
      "y": 86,
      "width": 40,
      "height": 41
    },
    "fill": "rgba(255, 255, 255, 1)",
    "strokeColor": "rgba(255, 255, 255, 1)",
    "strokeWidth": 0,
    "lineJoin": "miter"
  },
  {
    "a": {
      "x": 126,
      "y": 146
    },
    "b": {
      "x": 124,
      "y": 188
    },
    "c": {
      "x": 138,
      "y": 200
    },
    "x": 153,
    "y": 168.33333333333334,
    "r": 1227.7777777777783,
    "boundingBox": {
      "x": 124,
      "y": 146,
      "width": 14,
      "height": 54
    },
    "fill": "rgba(220, 218, 221, 1)",
    "strokeColor": "rgba(220, 218, 221, 1)",
    "strokeWidth": 0,
    "lineJoin": "miter"
  },
  {
    "a": {
      "x": 138,
      "y": 200
    },
    "b": {
      "x": 136,
      "y": 216
    },
    "c": {
      "x": 194,
      "y": 220
    },
    "x": 165.44444444444446,
    "y": 211.55555555555554,
    "r": 886.7283950617289,
    "boundingBox": {
      "x": 136,
      "y": 200,
      "width": 58,
      "height": 20
    },
    "fill": "rgba(57, 55, 58, 1)",
    "strokeColor": "rgba(57, 55, 58, 1)",
    "strokeWidth": 0,
    "lineJoin": "miter"
  },
  {
    "a": {
      "x": 136,
      "y": 216
    },
    "b": {
      "x": 152,
      "y": 244
    },
    "c": {
      "x": 194,
      "y": 220
    },
    "x": 165,
    "y": 218,
    "r": 845,
    "boundingBox": {
      "x": 136,
      "y": 216,
      "width": 58,
      "height": 28
    },
    "fill": "rgba(35, 33, 36, 1)",
    "strokeColor": "rgba(35, 33, 36, 1)",
    "strokeWidth": 0,
    "lineJoin": "miter"
  },
  {
    "a": {
      "x": 67,
      "y": -36
    },
    "b": {
      "x": 102,
      "y": 14
    },
    "c": {
      "x": 185,
      "y": -95
    },
    "x": 135.42592592592592,
    "y": -46.648148148148145,
    "r": 4795.490397805212,
    "boundingBox": {
      "x": 67,
      "y": -95,
      "width": 118,
      "height": 109
    },
    "fill": "rgba(248, 246, 249, 1)",
    "strokeColor": "rgba(248, 246, 249, 1)",
    "strokeWidth": 0,
    "lineJoin": "miter"
  },
  {
    "a": {
      "x": 126,
      "y": 146
    },
    "b": {
      "x": 138,
      "y": 200
    },
    "c": {
      "x": 178,
      "y": 127
    },
    "x": 162.83300395256916,
    "y": 166.14822134387353,
    "r": 1762.621003491696,
    "boundingBox": {
      "x": 126,
      "y": 127,
      "width": 52,
      "height": 73
    },
    "fill": "rgba(54, 52, 55, 1)",
    "strokeColor": "rgba(54, 52, 55, 1)",
    "strokeWidth": 0,
    "lineJoin": "miter"
  },
  {
    "a": {
      "x": 178,
      "y": 127
    },
    "b": {
      "x": 194,
      "y": 220
    },
    "c": {
      "x": 222,
      "y": 222
    },
    "x": 211.70878693623638,
    "y": 169.07698289269052,
    "r": 2906.754806064351,
    "boundingBox": {
      "x": 178,
      "y": 127,
      "width": 44,
      "height": 95
    },
    "fill": "rgba(53, 51, 54, 1)",
    "strokeColor": "rgba(53, 51, 54, 1)",
    "strokeWidth": 0,
    "lineJoin": "miter"
  },
  {
    "a": {
      "x": 194,
      "y": 220
    },
    "b": {
      "x": 152,
      "y": 244
    },
    "c": {
      "x": 222,
      "y": 222
    },
    "x": 203.4126984126984,
    "y": 285.22222222222223,
    "r": 4342.537163013354,
    "boundingBox": {
      "x": 152,
      "y": 220,
      "width": 70,
      "height": 24
    },
    "fill": "rgba(33, 31, 34, 1)",
    "strokeColor": "rgba(33, 31, 34, 1)",
    "strokeWidth": 0,
    "lineJoin": "miter"
  },
  {
    "a": {
      "x": 132,
      "y": 48
    },
    "b": {
      "x": 146,
      "y": 86
    },
    "c": {
      "x": 222,
      "y": 0
    },
    "x": 189.9266862170088,
    "y": 48.23753665689149,
    "r": 3355.557399747165,
    "boundingBox": {
      "x": 132,
      "y": 0,
      "width": 90,
      "height": 86
    },
    "fill": "rgba(255, 255, 255, 1)",
    "strokeColor": "rgba(255, 255, 255, 1)",
    "strokeWidth": 0,
    "lineJoin": "miter"
  },
  {
    "a": {
      "x": 146,
      "y": 86
    },
    "b": {
      "x": 178,
      "y": 127
    },
    "c": {
      "x": 222,
      "y": 0
    },
    "x": 211.83861622358555,
    "y": 67.6015678254942,
    "r": 4673.225692716473,
    "boundingBox": {
      "x": 146,
      "y": 0,
      "width": 76,
      "height": 127
    },
    "fill": "rgba(255, 255, 255, 1)",
    "strokeColor": "rgba(255, 255, 255, 1)",
    "strokeWidth": 0,
    "lineJoin": "miter"
  },
  {
    "a": {
      "x": 102,
      "y": 14
    },
    "b": {
      "x": 132,
      "y": 48
    },
    "c": {
      "x": 222,
      "y": 0
    },
    "x": 160.33866666666665,
    "y": -7.24,
    "r": 3854.537628444443,
    "boundingBox": {
      "x": 102,
      "y": 0,
      "width": 120,
      "height": 48
    },
    "fill": "rgba(252, 252, 252, 1)",
    "strokeColor": "rgba(252, 252, 252, 1)",
    "strokeWidth": 0,
    "lineJoin": "miter"
  },
  {
    "a": {
      "x": 185,
      "y": -95
    },
    "b": {
      "x": 102,
      "y": 14
    },
    "c": {
      "x": 222,
      "y": 0
    },
    "x": 157.72176539687868,
    "y": -29.670582312468536,
    "r": 5012.034898454874,
    "boundingBox": {
      "x": 102,
      "y": -95,
      "width": 120,
      "height": 109
    },
    "fill": "rgba(233, 231, 234, 1)",
    "strokeColor": "rgba(233, 231, 234, 1)",
    "strokeWidth": 0,
    "lineJoin": "miter"
  },
  {
    "a": {
      "x": 178,
      "y": 127
    },
    "b": {
      "x": 138,
      "y": 200
    },
    "c": {
      "x": 194,
      "y": 220
    },
    "x": 178.57978723404256,
    "y": 174.77659574468086,
    "r": 2282.939254187416,
    "boundingBox": {
      "x": 138,
      "y": 127,
      "width": 56,
      "height": 93
    },
    "fill": "rgba(53, 51, 54, 1)",
    "strokeColor": "rgba(53, 51, 54, 1)",
    "strokeWidth": 0,
    "lineJoin": "miter"
  },
  {
    "a": {
      "x": 132,
      "y": 48
    },
    "b": {
      "x": 132,
      "y": 56
    },
    "c": {
      "x": 146,
      "y": 86
    },
    "x": 179.71428571428572,
    "y": 52,
    "r": 2292.6530612244906,
    "boundingBox": {
      "x": 132,
      "y": 48,
      "width": 14,
      "height": 38
    },
    "fill": "rgba(72, 70, 73, 1)",
    "strokeColor": "rgba(72, 70, 73, 1)",
    "strokeWidth": 0,
    "lineJoin": "miter"
  },
  {
    "a": {
      "x": 152,
      "y": 244
    },
    "b": {
      "x": 129,
      "y": 275
    },
    "c": {
      "x": 222,
      "y": 222
    },
    "x": 212.00120192307693,
    "y": 312.54927884615387,
    "r": 8299.14786254161,
    "boundingBox": {
      "x": 129,
      "y": 222,
      "width": 93,
      "height": 53
    },
    "fill": "rgba(35, 33, 36, 1)",
    "strokeColor": "rgba(35, 33, 36, 1)",
    "strokeWidth": 0,
    "lineJoin": "miter"
  },
  {
    "a": {
      "x": 185,
      "y": -95
    },
    "b": {
      "x": 222,
      "y": 0
    },
    "c": {
      "x": 296,
      "y": 96
    },
    "x": 566.100632547441,
    "y": -188.72340425531914,
    "r": 154021.76863326563,
    "boundingBox": {
      "x": 185,
      "y": -95,
      "width": 111,
      "height": 191
    },
    "fill": "rgba(200, 198, 201, 1)",
    "strokeColor": "rgba(200, 198, 201, 1)",
    "strokeWidth": 0,
    "lineJoin": "miter"
  },
  {
    "a": {
      "x": 178,
      "y": 127
    },
    "b": {
      "x": 222,
      "y": 222
    },
    "c": {
      "x": 296,
      "y": 96
    },
    "x": 247.74176872912358,
    "y": 152.38802290440591,
    "r": 5508.466012461198,
    "boundingBox": {
      "x": 178,
      "y": 96,
      "width": 118,
      "height": 126
    },
    "fill": "rgba(251, 251, 251, 1)",
    "strokeColor": "rgba(251, 251, 251, 1)",
    "strokeWidth": 0,
    "lineJoin": "miter"
  },
  {
    "a": {
      "x": 222,
      "y": 0
    },
    "b": {
      "x": 178,
      "y": 127
    },
    "c": {
      "x": 296,
      "y": 96
    },
    "x": 226.83203641168697,
    "y": 72.79613859932462,
    "r": 5322.626370855949,
    "boundingBox": {
      "x": 178,
      "y": 0,
      "width": 118,
      "height": 127
    },
    "fill": "rgba(245, 243, 246, 1)",
    "strokeColor": "rgba(245, 243, 246, 1)",
    "strokeWidth": 0,
    "lineJoin": "miter"
  }
]